setup.py
abBleGatewaySdkPython/__init__.py
ab_ble_gateway_sdk_python.egg-info/PKG-INFO
ab_ble_gateway_sdk_python.egg-info/SOURCES.txt
ab_ble_gateway_sdk_python.egg-info/dependency_links.txt
ab_ble_gateway_sdk_python.egg-info/top_level.txt