Metadata-Version: 1.0
Name: ab-ble-gateway-sdk-python
Version: 0.0.1
Summary: ab ble gatwway sdk
Home-page: UNKNOWN
Author: jingzhixiang
Author-email: 945627077@qq.com
License: Apache-v2.0
Keywords: ab,ble,gateway
Platform: any
